{
  "events": [
    {
      "id": "tm-Z698xZb_Z16vP--eCf",
      "title": "STING 3.0 TOUR",
      "description": "Arrangement på Hamar",
      "date": "2026-06-30",
      "time": "18:00",
      "endTime": null,
      "location": "Hamar",
      "categories": [
        "konsert",
        "uteliv"
      ],
      "ticketUrl": "https://www.ticketmaster.no/event/sting-30-tour-tickets/1961842394?language=en-us",
      "affiliateUrl": "https://www.ticketmaster.no/event/sting-30-tour-tickets/1961842394?language=en-us&ref=hvaSkjerIByenMin",
      "imageUrl": "https://s1.ticketm.net/dam/a/0ca/42733b41-0ce3-4f12-a608-daaf529e60ca_TABLET_LANDSCAPE_16_9.jpg",
      "imageEmoji": "🎵",
      "sponsored": false,
      "featured": false,
      "source": "ticketmaster"
    },
    {
      "id": "tm-Z698xZb_Z16v_VZM_a",
      "title": "Oktoberfest Hamar 2026 | FREDAG",
      "description": "Arrangement på Vikingskipet, Hamar",
      "date": "2026-10-09",
      "time": "17:00",
      "endTime": null,
      "location": "Vikingskipet, Hamar",
      "categories": [
        "konsert"
      ],
      "ticketUrl": "https://www.ticketmaster.no/event/oktoberfest-hamar-2026-%7C-fredag-tickets/1674037649?language=en-us",
      "affiliateUrl": "https://www.ticketmaster.no/event/oktoberfest-hamar-2026-%7C-fredag-tickets/1674037649?language=en-us&ref=hvaSkjerIByenMin",
      "imageUrl": "https://s1.ticketm.net/dam/e/8a1/009a2fad-1f03-40be-be1c-95337aaf88a1_TABLET_LANDSCAPE_LARGE_16_9.jpg",
      "imageEmoji": "🎪",
      "sponsored": false,
      "featured": false,
      "source": "ticketmaster"
    },
    {
      "id": "tm-Z698xZb_Z16v_g4Ar7",
      "title": "Oktoberfest 2026 | HELGEPASS",
      "description": "Arrangement på Vikingskipet, Hamar",
      "date": "2026-10-10",
      "time": "00:00",
      "endTime": null,
      "location": "Vikingskipet, Hamar",
      "categories": [
        "konsert"
      ],
      "ticketUrl": "https://www.ticketmaster.no/event/oktoberfest-2026-%7C-helgepass-tickets/1675545784?language=en-us",
      "affiliateUrl": "https://www.ticketmaster.no/event/oktoberfest-2026-%7C-helgepass-tickets/1675545784?language=en-us&ref=hvaSkjerIByenMin",
      "imageUrl": "https://s1.ticketm.net/dam/e/994/c6fffa95-49d7-4268-8240-60765472d994_RETINA_LANDSCAPE_16_9.jpg",
      "imageEmoji": "🎪",
      "sponsored": false,
      "featured": false,
      "source": "ticketmaster"
    },
    {
      "id": "tm-Z698xZb_Z16vqwjFa4",
      "title": "Oktoberfest Hamar 2026 | LØRDAG",
      "description": "Arrangement på Vikingskipet, Hamar",
      "date": "2026-10-10",
      "time": "16:00",
      "endTime": null,
      "location": "Vikingskipet, Hamar",
      "categories": [
        "konsert"
      ],
      "ticketUrl": "https://www.ticketmaster.no/event/oktoberfest-hamar-2026-%7C-lrdag-tickets/1772708255?language=en-us",
      "affiliateUrl": "https://www.ticketmaster.no/event/oktoberfest-hamar-2026-%7C-lrdag-tickets/1772708255?language=en-us&ref=hvaSkjerIByenMin",
      "imageUrl": "https://s1.ticketm.net/dam/e/e52/069c1eb6-8805-47d6-adf4-33d01932ae52_RETINA_LANDSCAPE_16_9.jpg",
      "imageEmoji": "🎪",
      "sponsored": false,
      "featured": false,
      "source": "ticketmaster"
    }
  ],
  "meta": {
    "city": "hamar",
    "count": 4,
    "fetchedAt": "2026-06-26T08:29:02.242Z",
    "sources": {
      "ticketmaster": 4,
      "eventbrite": 0,
      "scrape": 0
    }
  }
}